configload/__init__.py
configload/configload.py
configload-0.0.1.dist-info/LICENSE
configload-0.0.1.dist-info/METADATA
configload-0.0.1.dist-info/WHEEL
configload-0.0.1.dist-info/top_level.txt
configload-0.0.1.dist-info/RECORD
