Metadata-Version: 2.1
Name: configload
Version: 0.0.1
Summary: install packages and run Python with them
Home-page: https://github.com/noahp/configload
Author: Noah Pendleton
Author-email: 2538614+noahp@users.noreply.github.com
License: UNKNOWN
Project-URL: Code, https://github.com/noahp/configload
Project-URL: Issue tracker, https://github.com/noahp/configload/issues
Platform: UNKNOWN
Classifier: Development Status :: 3 - Alpha
Classifier: License :: OSI Approved :: MIT License
Classifier: Programming Language :: Python :: 3.8
Classifier: Programming Language :: Python :: 3 :: Only
Requires-Python: >=3.8
Provides-Extra: toml
Requires-Dist: tomlkit ; extra == 'toml'
Provides-Extra: yaml
Requires-Dist: pyyaml ; extra == 'yaml'
